beexai/__init__.py
beexai/dataset/__init__.py
beexai/dataset/dataset.py
beexai/dataset/load_data.py
beexai/evaluate/__init__.py
beexai/evaluate/plot_metric.py
beexai/evaluate/metrics/__init__.py
beexai/evaluate/metrics/auc_tp.py
beexai/evaluate/metrics/complexity.py
beexai/evaluate/metrics/comprehensiveness.py
beexai/evaluate/metrics/faithfulnesscorr.py
beexai/evaluate/metrics/get_results.py
beexai/evaluate/metrics/infidelity.py
beexai/evaluate/metrics/metrics.py
beexai/evaluate/metrics/monotonicity.py
beexai/evaluate/metrics/sensitivity.py
beexai/evaluate/metrics/sparseness.py
beexai/evaluate/metrics/sufficiency.py
beexai/explanation/__init__.py
beexai/explanation/explaining.py
beexai/explanation/plot_attr.py
beexai/training/__init__.py
beexai/training/models.py
beexai/training/train.py
beexai/utils/__init__.py
beexai/utils/convert.py
beexai/utils/path.py
beexai/utils/sampling.py
beexai/utils/time_seed.py
beexai-0.0.6.dist-info/METADATA
beexai-0.0.6.dist-info/WHEEL
beexai-0.0.6.dist-info/licenses/LICENSE
beexai-0.0.6.dist-info/RECORD
