Metadata-Version: 2.1
Name: beexai
Version: 0.0.6
Summary: BEExAI: Benchmark to Evaluate Explainable AI
Project-URL: Homepage, https://github.com/SquareResearchCenter-AI/BEExAI
Project-URL: Issues, https://github.com/SquareResearchCenter-AI/BEExAI/issues
Author-email: Samuel Sithakoul <samuelabc78310@gmail.com>
License-File: LICENSE
Classifier: License :: OSI Approved :: BSD License
Classifier: Operating System :: OS Independent
Classifier: Programming Language :: Python :: 3
Requires-Python: >=3.9
Requires-Dist: captum>=0.6.0
Requires-Dist: joblib>=1.3.2
Requires-Dist: matplotlib>=3.8.3
Requires-Dist: numpy>=1.26.4
Requires-Dist: openml>=0.14.1
Requires-Dist: pandas>=2.2.1
Requires-Dist: plotly>=5.18.0
Requires-Dist: pyyaml>=6.0.1
Requires-Dist: scikit-learn>=1.3.0
Requires-Dist: seaborn>=0.13.2
Requires-Dist: torch>=2.0.1
Requires-Dist: tqdm>=4.66.1
Requires-Dist: xgboost>=2.0.3
